BeautyPrinting.py
BeautyPrinting/ProgressBar.py
BeautyPrinting-1.4.1.dist-info/LICENSE
BeautyPrinting-1.4.1.dist-info/METADATA
BeautyPrinting-1.4.1.dist-info/WHEEL
BeautyPrinting-1.4.1.dist-info/top_level.txt
BeautyPrinting-1.4.1.dist-info/RECORD
