Metadata-Version: 2.1
Name: BeautyPrinting
Version: 1.4.1
Summary: BeautyPrinting · 一个专为美观打印而设计的模块
Home-page: UNKNOWN
Author: YunDuanModule
License: UNKNOWN
Keywords: BeautyPrinting,Beauty,Printing,Print,beautiful,colorful,loading,bar,enlighten,bash,color,ProgressBar
Platform: UNKNOWN
Classifier: Programming Language :: Python :: 3
Classifier: License :: OSI Approved :: MIT License
Classifier: Operating System :: OS Independent
Requires-Python: >=3.6
License-File: LICENSE
Requires-Dist: colorama
Requires-Dist: enlighten
